<?xml version='1.0' encoding='UTF-8' ?>
<openerp>
    <data noupdate="0">

        <record id="view_partner_form" model="ir.ui.view">
            <field name="name">res.partner.form (ficep_coordinate)</field>
            <field name="model">res.partner</field>
            <field name="inherit_id" ref="base.view_partner_form" />
            <field name="arch" type="xml">

                <xpath expr="//page[@name='internal_notes']" position="attributes">
                    <attribute name="autofocus">autofocus</attribute>
                </xpath>

                <xpath expr="//page[@name='internal_notes']" position="after">
                    <page name="coordinates" string="Coordinates" invisible="context.get('popup')">
                        <separator name="email" string="Email Coordinates"/>
                        <separator name="address" string="Postal Coordinates"/>
                        <separator name="phone" string="Phone Coordinates"/>
                    </page>
                </xpath>

            </field>
        </record>

    </data>
</openerp>
